{"type":"FeatureCollection","features":[{"geometry":{"type":"LineString","coordinates":[[-0.1425243,51.5087420],[-0.1428223,51.5090290]]},"type":"Feature","id":"211559610","clipped":true,"properties":{"kind":"minor_road","sort_key":-6.0000000,"is_link":"no","is_tunnel":"no","is_bridge":"no","railway":null,"highway":"unclassified"}},{"geometry":{"type":"LineString","coordinates":[[-0.1416089,51.5087420],[-0.1418346,51.5089341],[-0.1428223,51.5099050]]},"type":"Feature","id":"4259144","clipped":true,"properties":{"kind":"minor_road","sort_key":-6.0000000,"is_link":"no","is_tunnel":"no","is_bridge":"no","railway":null,"highway":"unclassified"}},{"geometry":{"type":"LineString","coordinates":[[-0.1411869,51.5099866],[-0.1414965,51.5098023],[-0.1420498,51.5102528]]},"type":"Feature","id":"70854122","clipped":true,"properties":{"kind":"minor_road","sort_key":-7.0000000,"is_link":"no","is_tunnel":"no","is_bridge":"no","railway":null,"highway":"service"}},{"geometry":{"type":"LineString","coordinates":[[-0.1418346,51.5089341],[-0.1411417,51.5092180]]},"type":"Feature","id":"4370951","clipped":true,"properties":{"kind":"path","sort_key":-9.0000000,"is_link":"no","is_tunnel":"no","is_bridge":"no","railway":null,"highway":"footway"}},{"geometry":{"type":"LineString","coordinates":[[-0.1414159,51.5095244],[-0.1411417,51.5092180],[-0.1408161,51.5088943],[-0.1406704,51.5087420]]},"type":"Feature","id":"4370943","clipped":true,"properties":{"kind":"minor_road","sort_key":-6.0000000,"is_link":"no","is_tunnel":"no","is_bridge":"no","railway":null,"highway":"unclassified"}},{"geometry":{"type":"LineString","coordinates":[[-0.1408161,51.5088943],[-0.1412467,51.5087420]]},"type":"Feature","id":"4370944","clipped":true,"properties":{"kind":"minor_road","sort_key":-6.0000000,"is_link":"no","is_tunnel":"no","is_bridge":"no","railway":null,"highway":"unclassified"}},{"geometry":{"type":"LineString","coordinates":[[-0.1407126,51.5104528],[-0.1402345,51.5099825]]},"type":"Feature","id":"4259268","clipped":true,"properties":{"kind":"minor_road","sort_key":-6.0000000,"is_link":"no","is_tunnel":"no","is_bridge":"no","railway":null,"highway":"unclassified"}},{"geometry":{"type":"LineString","coordinates":[[-0.1409172,51.5097291],[-0.1411869,51.5099866],[-0.1416357,51.5104528]]},"type":"Feature","id":"4259269","clipped":true,"properties":{"kind":"minor_road","sort_key":-6.0000000,"is_link":"no","is_tunnel":"no","is_bridge":"no","railway":null,"highway":"unclassified"}},{"geometry":{"type":"LineString","coordinates":[[-0.1414159,51.5095244],[-0.1412547,51.5095989],[-0.1409756,51.5097103],[-0.1409172,51.5097291],[-0.1405691,51.5098493],[-0.1402345,51.5099825],[-0.1400852,51.5100383],[-0.1400757,51.5100415]]},"type":"Feature","id":"4370890","clipped":true,"properties":{"kind":"minor_road","sort_key":-6.0000000,"is_link":"no","is_tunnel":"no","is_bridge":"no","railway":null,"highway":"unclassified"}},{"geometry":{"type":"LineString","coordinates":[[-0.1424795,51.5103491],[-0.1414159,51.5095244]]},"type":"Feature","id":"4370942","clipped":true,"properties":{"kind":"minor_road","sort_key":-6.0000000,"is_link":"no","is_tunnel":"no","is_bridge":"no","railway":null,"highway":"unclassified"}},{"geometry":{"type":"LineString","coordinates":[[-0.1425806,51.5104528],[-0.1424795,51.5103491]]},"type":"Feature","id":"4370940","clipped":true,"properties":{"kind":"path","sort_key":-9.0000000,"is_link":"no","is_tunnel":"no","is_bridge":"no","railway":null,"highway":"pedestrian"}},{"geometry":{"type":"LineString","coordinates":[[-0.1428223,51.5102070],[-0.1424795,51.5103491]]},"type":"Feature","id":"4370941","clipped":true,"properties":{"kind":"minor_road","sort_key":-6.0000000,"is_link":"no","is_tunnel":"no","is_bridge":"no","railway":null,"highway":"unclassified"}},{"geometry":{"type":"LineString","coordinates":[[-0.1409756,51.5097103],[-0.1400757,51.5088440]]},"type":"Feature","id":"4370891","clipped":true,"properties":{"kind":"path","sort_key":-9.0000000,"is_link":"no","is_tunnel":"no","is_bridge":"no","railway":null,"highway":"footway"}}]}